README.md
setup.py
Chronoclust.egg-info/PKG-INFO
Chronoclust.egg-info/SOURCES.txt
Chronoclust.egg-info/dependency_links.txt
Chronoclust.egg-info/requires.txt
Chronoclust.egg-info/top_level.txt
chronoclust/__init__.py
chronoclust/app.py
chronoclust/clustering/__init__.py
chronoclust/clustering/hddstream.py
chronoclust/clustering/predecon.py
chronoclust/objects/__init__.py
chronoclust/objects/cluster.py
chronoclust/objects/microcluster.py
chronoclust/objects/predecon_mc.py
chronoclust/scaling/__init__.py
chronoclust/scaling/scaler.py
chronoclust/tests/__init__.py
chronoclust/tests/clustering_test/__init__.py
chronoclust/tests/clustering_test/unittest_hddstream.py
chronoclust/tests/clustering_test/unittest_predecon.py
chronoclust/tests/integration_test/__init__.py
chronoclust/tests/integration_test/no_cluster_test.py
chronoclust/tests/integration_test/normal_test.py
chronoclust/tests/objects_test/__init__.py
chronoclust/tests/objects_test/unittest_microcluster.py
chronoclust/tests/tracking_test/__init__.py
chronoclust/tests/tracking_test/unittest_track_by_historical_assoc.py
chronoclust/tests/tracking_test/unittest_track_by_lineage.py
chronoclust/tracking/__init__.py
chronoclust/tracking/cluster_tracker.py
chronoclust/utilities/__init__.py
chronoclust/utilities/mc_functions.py
chronoclust/utilities/predeconmc_functions.py