Metadata-Version: 2.1
Name: Chronoclust
Version: 0.2.1.2
Summary: A clustering algorithm that will perform clustering on each of a time-series of discrete datasets, and explicitly track the evolution of clusters over time.
Home-page: https://https://github.com/ghar1821/Chronoclust
Author: Givanna Putri
Author-email: ghar1821@uni.sydney.edu.au
License: UNKNOWN
Platform: UNKNOWN
Classifier: Development Status :: 5 - Production/Stable
Classifier: License :: OSI Approved :: GNU General Public License v3 (GPLv3)
Classifier: Programming Language :: Python :: 3.7
Requires-Python: >=3.6
